MANIFEST.in
README.rst
setup.py
marturion/__init__.py
marturion/admin.py
marturion/models.py
marturion.egg-info/PKG-INFO
marturion.egg-info/SOURCES.txt
marturion.egg-info/dependency_links.txt
marturion.egg-info/not-zip-safe
marturion.egg-info/top_level.txt
marturion/templatetags/__init__.py
marturion/templatetags/marturion_tags.py