Metadata-Version: 1.0
Name: marturion
Version: 0.1.3
Summary: a testimonals app
Home-page: http://github.com/eldarion/marturion
Author: Eldarion
Author-email: developers@eldarion.com
License: BSD
Platform: UNKNOWN
Classifier: Development Status :: 3 - Alpha
Classifier: Environment :: Web Environment
Classifier: Intended Audience :: Developers
Classifier: License :: OSI Approved :: BSD License
Classifier: Operating System :: OS Independent
Classifier: Programming Language :: Python
Classifier: Framework :: Django
